django_rest_framework_paginations-0.0.1.dist-info/DESCRIPTION.rst
django_rest_framework_paginations-0.0.1.dist-info/METADATA
django_rest_framework_paginations-0.0.1.dist-info/metadata.json
django_rest_framework_paginations-0.0.1.dist-info/RECORD
django_rest_framework_paginations-0.0.1.dist-info/top_level.txt
django_rest_framework_paginations-0.0.1.dist-info/WHEEL
rest_framework_paginations/__init__.py
rest_framework_paginations/paginations.py
